langsmith/__init__.py
langsmith/wrappers/__init__.py
langsmith/wrappers/base.py
langsmith/wrappers/openai.py
langsmith_wrappers-0.0.1.dist-info/LICENSE
langsmith_wrappers-0.0.1.dist-info/METADATA
langsmith_wrappers-0.0.1.dist-info/WHEEL
langsmith_wrappers-0.0.1.dist-info/RECORD
